buildarr_sonarr/__init__.py
buildarr_sonarr/api.py
buildarr_sonarr/cli.py
buildarr_sonarr/config/__init__.py
buildarr_sonarr/config/connect.py
buildarr_sonarr/config/download_clients/__init__.py
buildarr_sonarr/config/download_clients/download_clients.py
buildarr_sonarr/config/download_clients/remote_path_mappings.py
buildarr_sonarr/config/general.py
buildarr_sonarr/config/import_lists.py
buildarr_sonarr/config/indexers.py
buildarr_sonarr/config/media_management.py
buildarr_sonarr/config/metadata.py
buildarr_sonarr/config/profiles/__init__.py
buildarr_sonarr/config/profiles/delay.py
buildarr_sonarr/config/profiles/language.py
buildarr_sonarr/config/profiles/quality.py
buildarr_sonarr/config/profiles/release.py
buildarr_sonarr/config/quality.py
buildarr_sonarr/config/tags.py
buildarr_sonarr/config/types.py
buildarr_sonarr/config/ui.py
buildarr_sonarr/config/util.py
buildarr_sonarr/exceptions.py
buildarr_sonarr/manager.py
buildarr_sonarr/plugin.py
buildarr_sonarr/py.typed
buildarr_sonarr/secrets.py
buildarr_sonarr/types.py
buildarr_sonarr-0.6.4.dist-info/LICENSE
buildarr_sonarr-0.6.4.dist-info/METADATA
buildarr_sonarr-0.6.4.dist-info/WHEEL
buildarr_sonarr-0.6.4.dist-info/entry_points.txt
buildarr_sonarr-0.6.4.dist-info/RECORD
