Metadata-Version: 2.1
Name: buildarr-sonarr
Version: 0.6.4
Summary: Sonarr PVR plugin for Buildarr
Home-page: https://buildarr.github.io
License: GPL-3.0-or-later
Keywords: buildarr,sonarr
Author: Callum Dickinson
Author-email: callum.dickinson.nz@gmail.com
Requires-Python: >=3.8,<4.0
Classifier: Development Status :: 4 - Beta
Classifier: Framework :: Pydantic
Classifier: Intended Audience :: End Users/Desktop
Classifier: License :: OSI Approved :: GNU General Public License v3 or later (GPLv3+)
Classifier: Natural Language :: English
Classifier: Operating System :: OS Independent
Classifier: Programming Language :: Python :: 3
Classifier: Programming Language :: Python :: 3.8
Classifier: Programming Language :: Python :: 3.9
Classifier: Programming Language :: Python :: 3.10
Classifier: Programming Language :: Python :: 3.11
Classifier: Programming Language :: Python :: 3.12
Classifier: Topic :: System :: Systems Administration
Classifier: Typing :: Typed
Requires-Dist: buildarr (>=0.7.1,<0.8.0)
Requires-Dist: json5 (>=0.9.7)
Project-URL: Changes, https://buildarr.github.io/plugins/sonarr/release-notes
Project-URL: Documentation, https://buildarr.github.io/plugins/sonarr
Project-URL: Issue Tracker, https://github.com/buildarr/buildarr-sonarr/issues
Project-URL: Repository, https://github.com/buildarr/buildarr-sonarr
